pki_tools/__init__.py
pki_tools/crl.py
pki_tools/exceptions.py
pki_tools/funcs/__init__.py
pki_tools/funcs/check_revocation.py
pki_tools/ocsp.py
pki_tools/types/__init__.py
pki_tools/types/certificate.py
pki_tools/types/certificates.py
pki_tools/types/chain.py
pki_tools/types/crl.py
pki_tools/types/crypto_parser.py
pki_tools/types/csr.py
pki_tools/types/enums.py
pki_tools/types/extensions.py
pki_tools/types/key_pair.py
pki_tools/types/name.py
pki_tools/types/ocsp.py
pki_tools/types/signature_algorithm.py
pki_tools/types/utils.py
pki_tools-1.1.2.dist-info/LICENSE
pki_tools-1.1.2.dist-info/METADATA
pki_tools-1.1.2.dist-info/WHEEL
pki_tools-1.1.2.dist-info/RECORD
