Metadata-Version: 2.3
Name: pki-tools
Version: 1.1.2
Summary: PKI tools for e.g. checking certificate CRL/OCSP revocation
License: MIT
Author: Michal Sadowski
Author-email: misad90@gmail.com
Requires-Python: >=3.9.3,<4.0.0
Classifier: Development Status :: 5 - Production/Stable
Classifier: Intended Audience :: Developers
Classifier: License :: OSI Approved :: MIT License
Classifier: Operating System :: OS Independent
Classifier: Programming Language :: Python :: 3
Classifier: Programming Language :: Python :: 3.10
Classifier: Programming Language :: Python :: 3.11
Classifier: Programming Language :: Python :: 3.12
Classifier: Programming Language :: Python :: 3.13
Classifier: Topic :: Security :: Cryptography
Requires-Dist: cryptography (>=42.0.0,<46.0.0)
Requires-Dist: httpx (>=0.28.1,<0.29.0)
Requires-Dist: loguru (>=0.7.3,<0.8.0)
Requires-Dist: pydantic (>=2.11.7,<3.0.0)
Requires-Dist: pytz (>=2025.2,<2026.0)
Requires-Dist: pyyaml (>=6.0.2,<7.0.0)
Project-URL: Bug Tracker, https://github.com/fulder/pki-tools/issues
Project-URL: Homepage, https://github.com/fulder/pki-tools
Project-URL: Repository, https://github.com/fulder/pki-tools
